{"logPart":0,"testID":"18031712212601","mapInfo":{"name":"corridors_SS","height":45.0,"width":45.0,"tileSize":4.409999847412109,"flip":false},"gameInfo":{"experiment":"SP Positioning","scene":"SP Experiment - Target Hunt - Factory","duration":180},"targetStatisticsLogs":[{"timestamp":31.0,"playerInitialX":0.0,"playerInitialY":0.0,"playerX":0.0,"playerY":0.0,"targetX":5.0,"targetY":3.0,"coveredTileDistance":0.0,"time":0.0,"speed":0.0}],"finalStatistics":{"totalShots":13,"totalHits":4,"accuracy":0.3076923191547394,"coveredDistance":0.0,"mediumKillTime":180.0,"mediumKillDistance":0.0}}